rtchange/__init__.py
rtchange/coding.py
rtchange/finder.py
rtchange/tests/__init__.py
rtchange/tests/test_finder.py
rtchange-0.1.0.dist-info/DESCRIPTION.rst
rtchange-0.1.0.dist-info/METADATA
rtchange-0.1.0.dist-info/RECORD
rtchange-0.1.0.dist-info/WHEEL
rtchange-0.1.0.dist-info/metadata.json
rtchange-0.1.0.dist-info/top_level.txt
