Metadata-Version: 2.0
Name: rtchange
Version: 0.1.0
Summary: Real-time change point detection
Home-page: UNKNOWN
Author: Yusuke Hanada
Author-email: hyusuk9872@gmail.com
License: The MIT License (https://opensource.org/licenses/MIT)
Keywords: change detection realtime
Platform: UNKNOWN
Classifier: Programming Language :: Python
Classifier: Programming Language :: Python :: 3
Classifier: Programming Language :: Python :: 3.4
Classifier: Programming Language :: Python :: 3.5
Classifier: Programming Language :: Python :: 3.6
Classifier: Programming Language :: Python :: Implementation :: CPython
Classifier: Topic :: Scientific/Engineering :: Information Analysis
Classifier: License :: OSI Approved :: MIT License
Requires-Dist: numpy
Provides-Extra: testing
Requires-Dist: flake8; extra == 'testing'
Requires-Dist: pytest; extra == 'testing'
